hedera/__init__.py
hedera/generated.py
hedera/sdk-2.50.0.jar
hedera_sdk_py-2.50.0.dist-info/LICENSE
hedera_sdk_py-2.50.0.dist-info/METADATA
hedera_sdk_py-2.50.0.dist-info/WHEEL
hedera_sdk_py-2.50.0.dist-info/top_level.txt
hedera_sdk_py-2.50.0.dist-info/RECORD
