Metadata-Version: 2.2
Name: hedera-sdk-py
Version: 2.50.0
Summary: Hedera SDK in Python
Home-page: https://github.com/wensheng/hedera-sdk-py
Author: Wensheng Wang
Author-email: wenshengwang@gmail.com
Project-URL: Bug Tracker, https://github.com/wensheng/hedera-sdk-py/issues
Classifier: Programming Language :: Python :: 3
Classifier: License :: OSI Approved :: Apache Software License
Classifier: Operating System :: OS Independent
Requires-Python: >=3.8
License-File: LICENSE
Requires-Dist: pyjnius>=1.6.1
Dynamic: author
Dynamic: author-email
Dynamic: classifier
Dynamic: description
Dynamic: description-content-type
Dynamic: home-page
Dynamic: project-url
Dynamic: requires-dist
Dynamic: requires-python
Dynamic: summary
